payler/__init__.py
payler/broker.py
payler/client.py
payler/commands.py
payler/config.py
payler/db.py
payler/errors.py
payler/logs.py
payler/metrics.py
payler/process.py
payler/runtime.py
payler/store.py
payler/structs.py
payler/utils.py
payler-0.2.0.dist-info/entry_points.txt
payler-0.2.0.dist-info/WHEEL
payler-0.2.0.dist-info/METADATA
payler-0.2.0.dist-info/RECORD
