Metadata-Version: 2.1
Name: payler
Version: 0.2.0
Summary: Move messages from one source to another one.
Home-page: https://tbobm.github.io/payler
License: MIT
Keywords: broker,data,rabbitmq,mongodb,spooler
Author: Theo "Bob" Massard
Author-email: tbobm@protonmail.com
Requires-Python: >=3.7,<4.0
Classifier: License :: OSI Approved :: MIT License
Classifier: Programming Language :: Python :: 3
Classifier: Programming Language :: Python :: 3.7
Classifier: Programming Language :: Python :: 3.8
Classifier: Programming Language :: Python :: 3.9
Requires-Dist: PyYAML (>=5.4.1,<6.0.0)
Requires-Dist: aio-pika (>=6.7.1,<7.0.0)
Requires-Dist: click (>=7.1.2,<8.0.0)
Requires-Dist: motor (>=2.3.1,<3.0.0)
Requires-Dist: pendulum (>=2.1.2,<3.0.0)
Requires-Dist: prometheus-client (>=0.9.0,<0.10.0)
Requires-Dist: pymongo (>=3.11.3,<4.0.0)
Project-URL: Repository, https://github.com/tbobm/payler
